{
  "fullNav": [
    {
      "name": "Tojj",
      "route": "prodinfo-container"
    },
    {
      "name": "Varför?",
      "route": "convincer-container"
    },
    {
      "name": "Om oss",
      "route": "about-container"
    },
    {
      "name": "Kontakt",
      "route": "contact-us"
    },
    {
      "name": "FAQ",
      "route": "faq"
    }
  ],
  "smallNav": [
    {
      "name": "Startsida",
      "route": "/"
    },
    {
      "name": "Kontakt",
      "route": "contact-us"
    }
  ]
}